g729lib/__init__.py
g729lib/api.py
g729lib-0.1.dist-info/METADATA
g729lib-0.1.dist-info/WHEEL
g729lib-0.1.dist-info/licenses/LICENSE.txt
g729lib-0.1.dist-info/RECORD
