Metadata-Version: 2.3
Name: g729lib
Version: 0.1
Summary: Python bindings for the libbcg729 audio codec C library
Project-URL: Homepage, https://github.com/schorschii/g729lib
Project-URL: Issues, https://github.com/schorschii/g729lib/issues
Author: https://github.com/schorschii
License:                     GNU GENERAL PUBLIC LICENSE
License-File: LICENSE.txt
Keywords: codec,decoder,encoder,g729,libbcg729
Requires-Python: >=3.7
